{"points":[
    {"x":0.07445,
     "y":0.32149},
    {"x":0.099831,
     "y":0.36041},
    {"x":0.11168,
     "y":0.39594},
    {"x":0.12521,
     "y":0.43486},
    {"x":0.1286,
     "y":0.47377},
    {"x":0.12183,
     "y":0.51269},
    {"x":0.11337,
     "y":0.54992},
    {"x":0.096447,
     "y":0.58545},
    {"x":0.08291,
     "y":0.61083},
    {"x":0.11168,
     "y":0.64636},
    {"x":0.14044,
     "y":0.67005},
    {"x":0.16751,
     "y":0.70558},
    {"x":0.17766,
     "y":0.7445},
    {"x":0.16751,
     "y":0.78511},
    {"x":0.1709,
     "y":0.81726},
    {"x":0.20812,
     "y":0.8291},
    {"x":0.2335,
     "y":0.85618},
    {"x":0.25212,
     "y":0.89509},
    {"x":0.2555,
     "y":0.93401},
    {"x":0.23689,
     "y":0.96785},
    {"x":0.23689,
     "y":1},
    {"x":0.27411,
     "y":0.98139},
    {"x":0.30288,
     "y":0.94755},
    {"x":0.32995,
     "y":0.91371},
    {"x":0.35195,
     "y":0.87479},
    {"x":0.37563,
     "y":0.83756},
    {"x":0.39255,
     "y":0.80034},
    {"x":0.40271,
     "y":0.76142},
    {"x":0.41117,
     "y":0.7242},
    {"x":0.41624,
     "y":0.68359},
    {"x":0.42809,
     "y":0.64636},
    {"x":0.4264,
     "y":0.60745},
    {"x":0.41117,
     "y":0.57191},
    {"x":0.39594,
     "y":0.53807},
    {"x":0.38748,
     "y":0.50761},
    {"x":0.37902,
     "y":0.4687},
    {"x":0.37056,
     "y":0.43147},
    {"x":0.36717,
     "y":0.39086},
    {"x":0.37733,
     "y":0.35025},
    {"x":0.40609,
     "y":0.32995},
    {"x":0.4467,
     "y":0.32657},
    {"x":0.47885,
     "y":0.31641},
    {"x":0.51438,
     "y":0.33333},
    {"x":0.5533,
     "y":0.3401},
    {"x":0.57191,
     "y":0.34179},
    {"x":0.5753,
     "y":0.30457},
    {"x":0.57022,
     "y":0.26734},
    {"x":0.59391,
     "y":0.24027},
    {"x":0.63283,
     "y":0.25381},
    {"x":0.63959,
     "y":0.23858},
    {"x":0.61591,
     "y":0.20305},
    {"x":0.5956,
     "y":0.17597},
    {"x":0.63621,
     "y":0.16751},
    {"x":0.67513,
     "y":0.15567},
    {"x":0.71574,
     "y":0.14213},
    {"x":0.75635,
     "y":0.13367},
    {"x":0.79357,
     "y":0.12521},
    {"x":0.83249,
     "y":0.11168},
    {"x":0.86971,
     "y":0.093063},
    {"x":0.90863,
     "y":0.077834},
    {"x":0.94924,
     "y":0.05753},
    {"x":0.9797,
     "y":0.023689},
    {"x":0.96108,
     "y":0.0067682},
    {"x":0.92217,
     "y":0.021997},
    {"x":0.88156,
     "y":0.011844},
    {"x":0.84602,
     "y":0},
    {"x":0.81895,
     "y":0.010152},
    {"x":0.79865,
     "y":0.040609},
    {"x":0.76142,
     "y":0.064298},
    {"x":0.7225,
     "y":0.079526},
    {"x":0.69543,
     "y":0.076142},
    {"x":0.70558,
     "y":0.050761},
    {"x":0.6802,
     "y":0.062606},
    {"x":0.65821,
     "y":0.079526},
    {"x":0.61929,
     "y":0.093063},
    {"x":0.57868,
     "y":0.094755},
    {"x":0.53976,
     "y":0.091371},
    {"x":0.50085,
     "y":0.086294},
    {"x":0.46024,
     "y":0.076142},
    {"x":0.42301,
     "y":0.062606},
    {"x":0.39763,
     "y":0.067682},
    {"x":0.37563,
     "y":0.093063},
    {"x":0.33672,
     "y":0.1066},
    {"x":0.29611,
     "y":0.11844},
    {"x":0.25719,
     "y":0.12521},
    {"x":0.21827,
     "y":0.12352},
    {"x":0.17766,
     "y":0.12183},
    {"x":0.1709,
     "y":0.081218},
    {"x":0.13536,
     "y":0.077834},
    {"x":0.14721,
     "y":0.1066},
    {"x":0.16244,
     "y":0.13875},
    {"x":0.1269,
     "y":0.15905},
    {"x":0.089679,
     "y":0.17428},
    {"x":0.050761,
     "y":0.18105},
    {"x":0.028765,
     "y":0.1709},
    {"x":0.032149,
     "y":0.20643},
    {"x":0.052453,
     "y":0.24365},
    {"x":0.05753,
     "y":0.27411},
    {"x":0.025381,
     "y":0.27411},
    {"x":0,
     "y":0.29272},
    {"x":0.027073,
     "y":0.31472},
    {"x":0.062606,
     "y":0.30288},
    {"x":0.07445,
     "y":0.32149}],
 "triangles":[
    {"p1":13,
     "p2":14,
     "p3":15},
    {"p1":7,
     "p2":8,
     "p3":9},
    {"p1":6,
     "p2":7,
     "p3":9},
    {"p1":4,
     "p2":5,
     "p3":35},
    {"p1":2,
     "p2":37,
     "p3":38},
    {"p1":1,
     "p2":2,
     "p3":38},
    {"p1":2,
     "p2":3,
     "p3":37},
    {"p1":97,
     "p2":98,
     "p3":101},
    {"p1":4,
     "p2":35,
     "p3":36},
    {"p1":3,
     "p2":4,
     "p3":36},
    {"p1":3,
     "p2":36,
     "p3":37},
    {"p1":12,
     "p2":15,
     "p3":27},
    {"p1":12,
     "p2":13,
     "p3":15},
    {"p1":11,
     "p2":32,
     "p3":33},
    {"p1":5,
     "p2":6,
     "p3":33},
    {"p1":11,
     "p2":29,
     "p3":32},
    {"p1":98,
     "p2":99,
     "p3":100},
    {"p1":98,
     "p2":100,
     "p3":101},
    {"p1":38,
     "p2":39,
     "p3":83},
    {"p1":41,
     "p2":42,
     "p3":46},
    {"p1":41,
     "p2":46,
     "p3":77},
    {"p1":41,
     "p2":77,
     "p3":78},
    {"p1":43,
     "p2":44,
     "p3":45},
    {"p1":42,
     "p2":43,
     "p3":45},
    {"p1":42,
     "p2":45,
     "p3":46},
    {"p1":15,
     "p2":26,
     "p3":27},
    {"p1":16,
     "p2":24,
     "p3":25},
    {"p1":16,
     "p2":17,
     "p3":24},
    {"p1":15,
     "p2":16,
     "p3":26},
    {"p1":16,
     "p2":25,
     "p3":26},
    {"p1":6,
     "p2":10,
     "p3":33},
    {"p1":10,
     "p2":11,
     "p3":33},
    {"p1":6,
     "p2":9,
     "p3":10},
    {"p1":5,
     "p2":34,
     "p3":35},
    {"p1":5,
     "p2":33,
     "p3":34},
    {"p1":11,
     "p2":12,
     "p3":28},
    {"p1":11,
     "p2":28,
     "p3":29},
    {"p1":12,
     "p2":27,
     "p3":28},
    {"p1":1,
     "p2":90,
     "p3":91},
    {"p1":86,
     "p2":89,
     "p3":90},
    {"p1":87,
     "p2":88,
     "p3":89},
    {"p1":86,
     "p2":87,
     "p3":89},
    {"p1":47,
     "p2":49,
     "p3":50},
    {"p1":47,
     "p2":48,
     "p3":49},
    {"p1":85,
     "p2":86,
     "p3":90},
    {"p1":1,
     "p2":85,
     "p3":90},
    {"p1":46,
     "p2":51,
     "p3":77},
    {"p1":46,
     "p2":47,
     "p3":51},
    {"p1":47,
     "p2":50,
     "p3":51},
    {"p1":17,
     "p2":23,
     "p3":24},
    {"p1":17,
     "p2":22,
     "p3":23},
    {"p1":17,
     "p2":18,
     "p3":22},
    {"p1":19,
     "p2":20,
     "p3":21},
    {"p1":18,
     "p2":19,
     "p3":21},
    {"p1":18,
     "p2":21,
     "p3":22},
    {"p1":29,
     "p2":30,
     "p3":32},
    {"p1":30,
     "p2":31,
     "p3":32},
    {"p1":39,
     "p2":40,
     "p3":81},
    {"p1":78,
     "p2":79,
     "p3":81},
    {"p1":79,
     "p2":80,
     "p3":81},
    {"p1":40,
     "p2":41,
     "p3":81},
    {"p1":41,
     "p2":78,
     "p3":81},
    {"p1":0,
     "p2":1,
     "p3":91},
    {"p1":0,
     "p2":97,
     "p3":101},
    {"p1":0,
     "p2":91,
     "p3":97},
    {"p1":92,
     "p2":96,
     "p3":97},
    {"p1":91,
     "p2":92,
     "p3":97},
    {"p1":38,
     "p2":83,
     "p3":84},
    {"p1":1,
     "p2":38,
     "p3":84},
    {"p1":1,
     "p2":84,
     "p3":85},
    {"p1":39,
     "p2":82,
     "p3":83},
    {"p1":39,
     "p2":81,
     "p3":82},
    {"p1":93,
     "p2":95,
     "p3":96},
    {"p1":92,
     "p2":93,
     "p3":96},
    {"p1":93,
     "p2":94,
     "p3":95},
    {"p1":58,
     "p2":65,
     "p3":66},
    {"p1":56,
     "p2":57,
     "p3":67},
    {"p1":57,
     "p2":58,
     "p3":67},
    {"p1":58,
     "p2":66,
     "p3":67},
    {"p1":55,
     "p2":56,
     "p3":68},
    {"p1":56,
     "p2":67,
     "p3":68},
    {"p1":53,
     "p2":54,
     "p3":70},
    {"p1":51,
     "p2":76,
     "p3":77},
    {"p1":51,
     "p2":75,
     "p3":76},
    {"p1":51,
     "p2":52,
     "p3":74},
    {"p1":51,
     "p2":74,
     "p3":75},
    {"p1":52,
     "p2":53,
     "p3":74},
    {"p1":55,
     "p2":68,
     "p3":69},
    {"p1":54,
     "p2":55,
     "p3":69},
    {"p1":54,
     "p2":69,
     "p3":70},
    {"p1":59,
     "p2":60,
     "p3":63},
    {"p1":60,
     "p2":61,
     "p3":62},
    {"p1":60,
     "p2":62,
     "p3":63},
    {"p1":58,
     "p2":64,
     "p3":65},
    {"p1":58,
     "p2":59,
     "p3":64},
    {"p1":59,
     "p2":63,
     "p3":64},
    {"p1":53,
     "p2":70,
     "p3":73},
    {"p1":53,
     "p2":73,
     "p3":74},
    {"p1":70,
     "p2":71,
     "p3":72},
    {"p1":70,
     "p2":72,
     "p3":73}]
}