{"points":[
    {"x":0,
     "y":0.46988},
    {"x":0.056225,
     "y":0.50201},
    {"x":0.1245,
     "y":0.53414},
    {"x":0.19076,
     "y":0.56827},
    {"x":0.25904,
     "y":0.58434},
    {"x":0.32731,
     "y":0.58635},
    {"x":0.31124,
     "y":0.60643},
    {"x":0.24297,
     "y":0.63253},
    {"x":0.17871,
     "y":0.67871},
    {"x":0.12249,
     "y":0.72289},
    {"x":0.092369,
     "y":0.77108},
    {"x":0.16064,
     "y":0.75502},
    {"x":0.22892,
     "y":0.74297},
    {"x":0.29719,
     "y":0.73494},
    {"x":0.36345,
     "y":0.70884},
    {"x":0.41968,
     "y":0.67068},
    {"x":0.42771,
     "y":0.69076},
    {"x":0.38353,
     "y":0.75502},
    {"x":0.36145,
     "y":0.82329},
    {"x":0.34337,
     "y":0.89157},
    {"x":0.33936,
     "y":0.95984},
    {"x":0.38755,
     "y":0.90763},
    {"x":0.44779,
     "y":0.84337},
    {"x":0.50201,
     "y":0.78916},
    {"x":0.53815,
     "y":0.7249},
    {"x":0.55823,
     "y":0.65663},
    {"x":0.57229,
     "y":0.70683},
    {"x":0.5743,
     "y":0.7751},
    {"x":0.59839,
     "y":0.83936},
    {"x":0.62249,
     "y":0.90763},
    {"x":0.65863,
     "y":0.95783},
    {"x":0.66667,
     "y":0.88956},
    {"x":0.6747,
     "y":0.82129},
    {"x":0.68876,
     "y":0.75301},
    {"x":0.68474,
     "y":0.68474},
    {"x":0.66867,
     "y":0.61647},
    {"x":0.68072,
     "y":0.6004},
    {"x":0.7249,
     "y":0.65462},
    {"x":0.77912,
     "y":0.7008},
    {"x":0.83936,
     "y":0.74096},
    {"x":0.90361,
     "y":0.77108},
    {"x":0.88353,
     "y":0.71888},
    {"x":0.8494,
     "y":0.65863},
    {"x":0.81928,
     "y":0.59036},
    {"x":0.77309,
     "y":0.53012},
    {"x":0.71285,
     "y":0.48193},
    {"x":0.72691,
     "y":0.46988},
    {"x":0.79518,
     "y":0.48795},
    {"x":0.86345,
     "y":0.49197},
    {"x":0.93173,
     "y":0.48795},
    {"x":1,
     "y":0.47791},
    {"x":0.95382,
     "y":0.44378},
    {"x":0.88554,
     "y":0.41165},
    {"x":0.81928,
     "y":0.3755},
    {"x":0.751,
     "y":0.35743},
    {"x":0.68273,
     "y":0.35341},
    {"x":0.67269,
     "y":0.33936},
    {"x":0.74096,
     "y":0.31325},
    {"x":0.80522,
     "y":0.27309},
    {"x":0.85743,
     "y":0.23293},
    {"x":0.90763,
     "y":0.18072},
    {"x":0.86145,
     "y":0.17871},
    {"x":0.79317,
     "y":0.19277},
    {"x":0.7249,
     "y":0.2008},
    {"x":0.65663,
     "y":0.22088},
    {"x":0.59438,
     "y":0.25703},
    {"x":0.55622,
     "y":0.27108},
    {"x":0.59639,
     "y":0.21084},
    {"x":0.63052,
     "y":0.14257},
    {"x":0.64659,
     "y":0.074297},
    {"x":0.66064,
     "y":0.0060241},
    {"x":0.62851,
     "y":0.014056},
    {"x":0.57831,
     "y":0.068273},
    {"x":0.51807,
     "y":0.1245},
    {"x":0.4739,
     "y":0.18876},
    {"x":0.44578,
     "y":0.25703},
    {"x":0.42771,
     "y":0.26707},
    {"x":0.42369,
     "y":0.1988},
    {"x":0.41365,
     "y":0.13052},
    {"x":0.38554,
     "y":0.062249},
    {"x":0.35542,
     "y":0},
    {"x":0.33534,
     "y":0.024096},
    {"x":0.32932,
     "y":0.092369},
    {"x":0.31526,
     "y":0.16064},
    {"x":0.30924,
     "y":0.22892},
    {"x":0.32129,
     "y":0.29719},
    {"x":0.34538,
     "y":0.36546},
    {"x":0.29518,
     "y":0.31526},
    {"x":0.24699,
     "y":0.25703},
    {"x":0.18474,
     "y":0.21888},
    {"x":0.12249,
     "y":0.18072},
    {"x":0.096386,
     "y":0.19478},
    {"x":0.13052,
     "y":0.25502},
    {"x":0.16667,
     "y":0.32129},
    {"x":0.20683,
     "y":0.38755},
    {"x":0.25703,
     "y":0.43775},
    {"x":0.30723,
     "y":0.48193},
    {"x":0.23896,
     "y":0.46185},
    {"x":0.17068,
     "y":0.44578},
    {"x":0.10241,
     "y":0.45181},
    {"x":0.034137,
     "y":0.45783},
    {"x":0,
     "y":0.46988}],
 "triangles":[
    {"p1":25,
     "p2":86,
     "p3":96},
    {"p1":17,
     "p2":18,
     "p3":22},
    {"p1":17,
     "p2":22,
     "p3":23},
    {"p1":25,
     "p2":36,
     "p3":45},
    {"p1":36,
     "p2":44,
     "p3":45},
    {"p1":49,
     "p2":50,
     "p3":51},
    {"p1":0,
     "p2":1,
     "p3":100},
    {"p1":5,
     "p2":25,
     "p3":96},
    {"p1":5,
     "p2":15,
     "p3":25},
    {"p1":16,
     "p2":17,
     "p3":23},
    {"p1":16,
     "p2":23,
     "p3":24},
    {"p1":15,
     "p2":16,
     "p3":25},
    {"p1":16,
     "p2":24,
     "p3":25},
    {"p1":9,
     "p2":10,
     "p3":11},
    {"p1":8,
     "p2":9,
     "p3":11},
    {"p1":8,
     "p2":11,
     "p3":12},
    {"p1":18,
     "p2":21,
     "p3":22},
    {"p1":58,
     "p2":59,
     "p3":62},
    {"p1":77,
     "p2":83,
     "p3":84},
    {"p1":77,
     "p2":78,
     "p3":83},
    {"p1":78,
     "p2":82,
     "p3":83},
    {"p1":45,
     "p2":55,
     "p3":66},
    {"p1":25,
     "p2":66,
     "p3":86},
    {"p1":25,
     "p2":45,
     "p3":66},
    {"p1":4,
     "p2":5,
     "p3":96},
    {"p1":29,
     "p2":30,
     "p3":31},
    {"p1":19,
     "p2":20,
     "p3":21},
    {"p1":18,
     "p2":19,
     "p3":21},
    {"p1":59,
     "p2":60,
     "p3":61},
    {"p1":59,
     "p2":61,
     "p3":62},
    {"p1":39,
     "p2":40,
     "p3":41},
    {"p1":27,
     "p2":32,
     "p3":33},
    {"p1":36,
     "p2":37,
     "p3":44},
    {"p1":37,
     "p2":43,
     "p3":44},
    {"p1":25,
     "p2":35,
     "p3":36},
    {"p1":25,
     "p2":34,
     "p3":35},
    {"p1":86,
     "p2":95,
     "p3":96},
    {"p1":1,
     "p2":2,
     "p3":99},
    {"p1":1,
     "p2":99,
     "p3":100},
    {"p1":79,
     "p2":80,
     "p3":81},
    {"p1":78,
     "p2":79,
     "p3":82},
    {"p1":79,
     "p2":81,
     "p3":82},
    {"p1":55,
     "p2":56,
     "p3":66},
    {"p1":56,
     "p2":57,
     "p3":64},
    {"p1":66,
     "p2":76,
     "p3":86},
    {"p1":66,
     "p2":75,
     "p3":76},
    {"p1":76,
     "p2":85,
     "p3":86},
    {"p1":76,
     "p2":84,
     "p3":85},
    {"p1":76,
     "p2":77,
     "p3":84},
    {"p1":5,
     "p2":6,
     "p3":15},
    {"p1":6,
     "p2":14,
     "p3":15},
    {"p1":27,
     "p2":28,
     "p3":32},
    {"p1":28,
     "p2":31,
     "p3":32},
    {"p1":28,
     "p2":29,
     "p3":31},
    {"p1":25,
     "p2":26,
     "p3":34},
    {"p1":26,
     "p2":33,
     "p3":34},
    {"p1":26,
     "p2":27,
     "p3":33},
    {"p1":49,
     "p2":51,
     "p3":52},
    {"p1":48,
     "p2":49,
     "p3":52},
    {"p1":47,
     "p2":52,
     "p3":53},
    {"p1":47,
     "p2":48,
     "p3":52},
    {"p1":39,
     "p2":41,
     "p3":42},
    {"p1":38,
     "p2":39,
     "p3":42},
    {"p1":37,
     "p2":38,
     "p3":43},
    {"p1":38,
     "p2":42,
     "p3":43},
    {"p1":46,
     "p2":47,
     "p3":53},
    {"p1":46,
     "p2":53,
     "p3":54},
    {"p1":45,
     "p2":46,
     "p3":55},
    {"p1":46,
     "p2":54,
     "p3":55},
    {"p1":89,
     "p2":90,
     "p3":92},
    {"p1":90,
     "p2":91,
     "p3":92},
    {"p1":4,
     "p2":96,
     "p3":97},
    {"p1":3,
     "p2":4,
     "p3":97},
    {"p1":69,
     "p2":70,
     "p3":71},
    {"p1":69,
     "p2":71,
     "p3":72},
    {"p1":66,
     "p2":74,
     "p3":75},
    {"p1":66,
     "p2":67,
     "p3":74},
    {"p1":67,
     "p2":73,
     "p3":74},
    {"p1":6,
     "p2":13,
     "p3":14},
    {"p1":86,
     "p2":87,
     "p3":95},
    {"p1":87,
     "p2":94,
     "p3":95},
    {"p1":88,
     "p2":89,
     "p3":93},
    {"p1":89,
     "p2":92,
     "p3":93},
    {"p1":87,
     "p2":93,
     "p3":94},
    {"p1":87,
     "p2":88,
     "p3":93},
    {"p1":2,
     "p2":3,
     "p3":98},
    {"p1":3,
     "p2":97,
     "p3":98},
    {"p1":2,
     "p2":98,
     "p3":99},
    {"p1":57,
     "p2":63,
     "p3":64},
    {"p1":57,
     "p2":58,
     "p3":63},
    {"p1":58,
     "p2":62,
     "p3":63},
    {"p1":56,
     "p2":65,
     "p3":66},
    {"p1":56,
     "p2":64,
     "p3":65},
    {"p1":68,
     "p2":72,
     "p3":73},
    {"p1":67,
     "p2":68,
     "p3":73},
    {"p1":68,
     "p2":69,
     "p3":72},
    {"p1":6,
     "p2":7,
     "p3":13},
    {"p1":7,
     "p2":8,
     "p3":12},
    {"p1":7,
     "p2":12,
     "p3":13}]
}