{"points":[
    {"x":0.27848,
     "y":0.50211},
    {"x":0.28692,
     "y":0.52743},
    {"x":0.29114,
     "y":0.55274},
    {"x":0.2827,
     "y":0.57806},
    {"x":0.27004,
     "y":0.60338},
    {"x":0.25738,
     "y":0.62869},
    {"x":0.24473,
     "y":0.65401},
    {"x":0.23207,
     "y":0.67932},
    {"x":0.2173,
     "y":0.70464},
    {"x":0.20253,
     "y":0.72996},
    {"x":0.18987,
     "y":0.75527},
    {"x":0.17722,
     "y":0.78059},
    {"x":0.15612,
     "y":0.79958},
    {"x":0.13291,
     "y":0.81013},
    {"x":0.11392,
     "y":0.8038},
    {"x":0.090717,
     "y":0.80802},
    {"x":0.094937,
     "y":0.83122},
    {"x":0.10759,
     "y":0.83966},
    {"x":0.086498,
     "y":0.83544},
    {"x":0.063291,
     "y":0.83966},
    {"x":0.065401,
     "y":0.86498},
    {"x":0.080169,
     "y":0.8692},
    {"x":0.059072,
     "y":0.87131},
    {"x":0.033755,
     "y":0.87342},
    {"x":0.035865,
     "y":0.89662},
    {"x":0.044304,
     "y":0.90928},
    {"x":0.023207,
     "y":0.90084},
    {"x":0,
     "y":0.91139},
    {"x":0.012658,
     "y":0.93038},
    {"x":0.012658,
     "y":0.94515},
    {"x":0.010549,
     "y":0.97046},
    {"x":0.031646,
     "y":0.98734},
    {"x":0.048523,
     "y":1},
    {"x":0.07384,
     "y":0.99156},
    {"x":0.099156,
     "y":0.99367},
    {"x":0.12025,
     "y":0.97468},
    {"x":0.13502,
     "y":0.94937},
    {"x":0.15401,
     "y":0.92405},
    {"x":0.17089,
     "y":0.90084},
    {"x":0.18987,
     "y":0.87764},
    {"x":0.20675,
     "y":0.85443},
    {"x":0.21941,
     "y":0.82911},
    {"x":0.23418,
     "y":0.80591},
    {"x":0.24895,
     "y":0.78059},
    {"x":0.2616,
     "y":0.75527},
    {"x":0.27637,
     "y":0.72996},
    {"x":0.29114,
     "y":0.70464},
    {"x":0.3038,
     "y":0.67932},
    {"x":0.32068,
     "y":0.65612},
    {"x":0.33333,
     "y":0.6308},
    {"x":0.3481,
     "y":0.60549},
    {"x":0.36076,
     "y":0.58017},
    {"x":0.37553,
     "y":0.55485},
    {"x":0.39873,
     "y":0.54008},
    {"x":0.42194,
     "y":0.5211},
    {"x":0.44515,
     "y":0.5},
    {"x":0.47046,
     "y":0.47679},
    {"x":0.49367,
     "y":0.4557},
    {"x":0.51477,
     "y":0.43249},
    {"x":0.53376,
     "y":0.4135},
    {"x":0.55063,
     "y":0.39241},
    {"x":0.56962,
     "y":0.3692},
    {"x":0.5865,
     "y":0.34388},
    {"x":0.60127,
     "y":0.32489},
    {"x":0.61392,
     "y":0.3038},
    {"x":0.62658,
     "y":0.2827},
    {"x":0.63924,
     "y":0.25949},
    {"x":0.64557,
     "y":0.2384},
    {"x":0.6519,
     "y":0.21519},
    {"x":0.65823,
     "y":0.18987},
    {"x":0.66034,
     "y":0.16456},
    {"x":0.66245,
     "y":0.13924},
    {"x":0.66245,
     "y":0.11392},
    {"x":0.65612,
     "y":0.088608},
    {"x":0.64557,
     "y":0.063291},
    {"x":0.62447,
     "y":0.037975},
    {"x":0.60549,
     "y":0.018987},
    {"x":0.58017,
     "y":0.0084388},
    {"x":0.55485,
     "y":0.0021097},
    {"x":0.52954,
     "y":0},
    {"x":0.50422,
     "y":0},
    {"x":0.4789,
     "y":0.0021097},
    {"x":0.45359,
     "y":0.0042194},
    {"x":0.42827,
     "y":0.0084388},
    {"x":0.40295,
     "y":0.012658},
    {"x":0.37764,
     "y":0.018987},
    {"x":0.35232,
     "y":0.029536},
    {"x":0.327,
     "y":0.042194},
    {"x":0.30802,
     "y":0.061181},
    {"x":0.28903,
     "y":0.084388},
    {"x":0.27637,
     "y":0.1097},
    {"x":0.26582,
     "y":0.13502},
    {"x":0.25949,
     "y":0.16034},
    {"x":0.25316,
     "y":0.18565},
    {"x":0.24895,
     "y":0.21097},
    {"x":0.24473,
     "y":0.23629},
    {"x":0.24262,
     "y":0.2616},
    {"x":0.24262,
     "y":0.28692},
    {"x":0.24051,
     "y":0.31224},
    {"x":0.24262,
     "y":0.33755},
    {"x":0.24684,
     "y":0.36287},
    {"x":0.24895,
     "y":0.38819},
    {"x":0.25316,
     "y":0.4135},
    {"x":0.25949,
     "y":0.43882},
    {"x":0.26582,
     "y":0.46414},
    {"x":0.27426,
     "y":0.48945},
    {"x":0.27848,
     "y":0.50211}],
 "triangles":[
    {"p1":71,
     "p2":78,
     "p3":79},
    {"p1":75,
     "p2":76,
     "p3":77},
    {"p1":75,
     "p2":77,
     "p3":78},
    {"p1":71,
     "p2":75,
     "p3":78},
    {"p1":64,
     "p2":83,
     "p3":92},
    {"p1":73,
     "p2":74,
     "p3":75},
    {"p1":71,
     "p2":72,
     "p3":73},
    {"p1":71,
     "p2":73,
     "p3":75},
    {"p1":70,
     "p2":80,
     "p3":81},
    {"p1":70,
     "p2":71,
     "p3":79},
    {"p1":70,
     "p2":79,
     "p3":80},
    {"p1":29,
     "p2":30,
     "p3":31},
    {"p1":25,
     "p2":29,
     "p3":31},
    {"p1":25,
     "p2":26,
     "p3":28},
    {"p1":25,
     "p2":28,
     "p3":29},
    {"p1":26,
     "p2":27,
     "p3":28},
    {"p1":62,
     "p2":93,
     "p3":94},
    {"p1":62,
     "p2":92,
     "p3":93},
    {"p1":63,
     "p2":64,
     "p3":92},
    {"p1":62,
     "p2":63,
     "p3":92},
    {"p1":62,
     "p2":94,
     "p3":95},
    {"p1":25,
     "p2":35,
     "p3":36},
    {"p1":12,
     "p2":39,
     "p3":40},
    {"p1":64,
     "p2":65,
     "p3":83},
    {"p1":65,
     "p2":67,
     "p3":83},
    {"p1":67,
     "p2":82,
     "p3":83},
    {"p1":68,
     "p2":70,
     "p3":81},
    {"p1":68,
     "p2":81,
     "p3":82},
    {"p1":67,
     "p2":68,
     "p3":82},
    {"p1":86,
     "p2":87,
     "p3":88},
    {"p1":83,
     "p2":84,
     "p3":92},
    {"p1":86,
     "p2":88,
     "p3":90},
    {"p1":84,
     "p2":90,
     "p3":92},
    {"p1":25,
     "p2":31,
     "p3":33},
    {"p1":25,
     "p2":33,
     "p3":35},
    {"p1":33,
     "p2":34,
     "p3":35},
    {"p1":31,
     "p2":32,
     "p3":33},
    {"p1":56,
     "p2":57,
     "p3":100},
    {"p1":61,
     "p2":62,
     "p3":95},
    {"p1":61,
     "p2":95,
     "p3":96},
    {"p1":56,
     "p2":102,
     "p3":103},
    {"p1":55,
     "p2":56,
     "p3":103},
    {"p1":1,
     "p2":2,
     "p3":52},
    {"p1":21,
     "p2":25,
     "p3":36},
    {"p1":21,
     "p2":36,
     "p3":37},
    {"p1":65,
     "p2":66,
     "p3":67},
    {"p1":68,
     "p2":69,
     "p3":70},
    {"p1":88,
     "p2":89,
     "p3":90},
    {"p1":90,
     "p2":91,
     "p3":92},
    {"p1":85,
     "p2":86,
     "p3":90},
    {"p1":84,
     "p2":85,
     "p3":90},
    {"p1":56,
     "p2":101,
     "p3":102},
    {"p1":56,
     "p2":100,
     "p3":101},
    {"p1":58,
     "p2":59,
     "p3":97},
    {"p1":57,
     "p2":58,
     "p3":100},
    {"p1":60,
     "p2":96,
     "p3":97},
    {"p1":60,
     "p2":61,
     "p3":96},
    {"p1":59,
     "p2":60,
     "p3":97},
    {"p1":55,
     "p2":103,
     "p3":104},
    {"p1":0,
     "p2":53,
     "p3":105},
    {"p1":0,
     "p2":52,
     "p3":53},
    {"p1":0,
     "p2":1,
     "p3":52},
    {"p1":17,
     "p2":18,
     "p3":21},
    {"p1":18,
     "p2":19,
     "p3":21},
    {"p1":22,
     "p2":24,
     "p3":25},
    {"p1":21,
     "p2":22,
     "p3":25},
    {"p1":22,
     "p2":23,
     "p3":24},
    {"p1":9,
     "p2":10,
     "p3":43},
    {"p1":10,
     "p2":42,
     "p3":43},
    {"p1":10,
     "p2":11,
     "p3":42},
    {"p1":17,
     "p2":38,
     "p3":39},
    {"p1":17,
     "p2":21,
     "p3":38},
    {"p1":21,
     "p2":37,
     "p3":38},
    {"p1":11,
     "p2":41,
     "p3":42},
    {"p1":12,
     "p2":40,
     "p3":41},
    {"p1":11,
     "p2":12,
     "p3":41},
    {"p1":58,
     "p2":99,
     "p3":100},
    {"p1":97,
     "p2":98,
     "p3":99},
    {"p1":58,
     "p2":97,
     "p3":99},
    {"p1":4,
     "p2":5,
     "p3":48},
    {"p1":5,
     "p2":6,
     "p3":47},
    {"p1":5,
     "p2":47,
     "p3":48},
    {"p1":9,
     "p2":43,
     "p3":44},
    {"p1":2,
     "p2":3,
     "p3":50},
    {"p1":4,
     "p2":48,
     "p3":49},
    {"p1":3,
     "p2":4,
     "p3":49},
    {"p1":3,
     "p2":49,
     "p3":50},
    {"p1":2,
     "p2":51,
     "p3":52},
    {"p1":2,
     "p2":50,
     "p3":51},
    {"p1":12,
     "p2":13,
     "p3":39},
    {"p1":13,
     "p2":17,
     "p3":39},
    {"p1":8,
     "p2":9,
     "p3":44},
    {"p1":8,
     "p2":44,
     "p3":45},
    {"p1":19,
     "p2":20,
     "p3":21},
    {"p1":14,
     "p2":15,
     "p3":16},
    {"p1":13,
     "p2":14,
     "p3":17},
    {"p1":14,
     "p2":16,
     "p3":17},
    {"p1":6,
     "p2":46,
     "p3":47},
    {"p1":53,
     "p2":54,
     "p3":105},
    {"p1":54,
     "p2":55,
     "p3":104},
    {"p1":54,
     "p2":104,
     "p3":105},
    {"p1":6,
     "p2":7,
     "p3":46},
    {"p1":7,
     "p2":8,
     "p3":45},
    {"p1":7,
     "p2":45,
     "p3":46}]
}