{"points":[
    {"x":0.012658,
     "y":0.22025},
    {"x":0.032911,
     "y":0.24304},
    {"x":0.055696,
     "y":0.26076},
    {"x":0.078481,
     "y":0.27089},
    {"x":0.10127,
     "y":0.27595},
    {"x":0.12405,
     "y":0.28354},
    {"x":0.14684,
     "y":0.28861},
    {"x":0.16962,
     "y":0.28861},
    {"x":0.19241,
     "y":0.29367},
    {"x":0.21519,
     "y":0.29873},
    {"x":0.23797,
     "y":0.30127},
    {"x":0.26076,
     "y":0.30633},
    {"x":0.28354,
     "y":0.30886},
    {"x":0.30633,
     "y":0.31646},
    {"x":0.32911,
     "y":0.31646},
    {"x":0.3519,
     "y":0.31899},
    {"x":0.37468,
     "y":0.32405},
    {"x":0.39747,
     "y":0.32658},
    {"x":0.42025,
     "y":0.32658},
    {"x":0.44051,
     "y":0.34177},
    {"x":0.46329,
     "y":0.36203},
    {"x":0.48608,
     "y":0.37975},
    {"x":0.50886,
     "y":0.39747},
    {"x":0.53165,
     "y":0.41772},
    {"x":0.5519,
     "y":0.44051},
    {"x":0.56709,
     "y":0.44051},
    {"x":0.55696,
     "y":0.41772},
    {"x":0.55949,
     "y":0.39494},
    {"x":0.57975,
     "y":0.38481},
    {"x":0.60253,
     "y":0.38481},
    {"x":0.62532,
     "y":0.38481},
    {"x":0.6481,
     "y":0.38228},
    {"x":0.67089,
     "y":0.38228},
    {"x":0.69367,
     "y":0.38228},
    {"x":0.71646,
     "y":0.38228},
    {"x":0.73924,
     "y":0.38228},
    {"x":0.76203,
     "y":0.38228},
    {"x":0.78481,
     "y":0.37975},
    {"x":0.80759,
     "y":0.37975},
    {"x":0.83038,
     "y":0.37975},
    {"x":0.85316,
     "y":0.37975},
    {"x":0.87595,
     "y":0.37722},
    {"x":0.89873,
     "y":0.37215},
    {"x":0.92152,
     "y":0.36709},
    {"x":0.9443,
     "y":0.36203},
    {"x":0.96709,
     "y":0.35443},
    {"x":0.98481,
     "y":0.33165},
    {"x":0.98987,
     "y":0.30886},
    {"x":0.98734,
     "y":0.28608},
    {"x":0.98987,
     "y":0.26329},
    {"x":0.99494,
     "y":0.24051},
    {"x":1,
     "y":0.21772},
    {"x":0.99494,
     "y":0.19494},
    {"x":0.98734,
     "y":0.17215},
    {"x":0.98734,
     "y":0.14937},
    {"x":0.98734,
     "y":0.12658},
    {"x":0.98481,
     "y":0.1038},
    {"x":0.97722,
     "y":0.081013},
    {"x":0.97215,
     "y":0.058228},
    {"x":0.95949,
     "y":0.035443},
    {"x":0.93924,
     "y":0.01519},
    {"x":0.91646,
     "y":0.0075949},
    {"x":0.89367,
     "y":0.0025316},
    {"x":0.87089,
     "y":0},
    {"x":0.8481,
     "y":0},
    {"x":0.82532,
     "y":0},
    {"x":0.80253,
     "y":0.0050633},
    {"x":0.77975,
     "y":0.0050633},
    {"x":0.75696,
     "y":0.010127},
    {"x":0.73418,
     "y":0.012658},
    {"x":0.71139,
     "y":0.020253},
    {"x":0.68861,
     "y":0.022785},
    {"x":0.66582,
     "y":0.03038},
    {"x":0.64304,
     "y":0.050633},
    {"x":0.62025,
     "y":0.060759},
    {"x":0.59747,
     "y":0.063291},
    {"x":0.57468,
     "y":0.063291},
    {"x":0.5519,
     "y":0.060759},
    {"x":0.52911,
     "y":0.058228},
    {"x":0.50633,
     "y":0.053165},
    {"x":0.48354,
     "y":0.04557},
    {"x":0.46076,
     "y":0.037975},
    {"x":0.43797,
     "y":0.03038},
    {"x":0.41519,
     "y":0.022785},
    {"x":0.39241,
     "y":0.01519},
    {"x":0.36962,
     "y":0.010127},
    {"x":0.34684,
     "y":0.010127},
    {"x":0.32405,
     "y":0.0075949},
    {"x":0.30127,
     "y":0.0075949},
    {"x":0.27848,
     "y":0.010127},
    {"x":0.2557,
     "y":0.012658},
    {"x":0.23291,
     "y":0.01519},
    {"x":0.21013,
     "y":0.020253},
    {"x":0.18734,
     "y":0.027848},
    {"x":0.16456,
     "y":0.035443},
    {"x":0.14177,
     "y":0.043038},
    {"x":0.11899,
     "y":0.050633},
    {"x":0.096203,
     "y":0.063291},
    {"x":0.073418,
     "y":0.073418},
    {"x":0.050633,
     "y":0.088608},
    {"x":0.027848,
     "y":0.10633},
    {"x":0.010127,
     "y":0.12911},
    {"x":0,
     "y":0.1519},
    {"x":0,
     "y":0.17468},
    {"x":0.0025316,
     "y":0.19747},
    {"x":0.012658,
     "y":0.22025},
    {"x":0.012658,
     "y":0.22025}],
 "triangles":[
    {"p1":57,
     "p2":62,
     "p3":63},
    {"p1":101,
     "p2":102,
     "p3":103},
    {"p1":1,
     "p2":100,
     "p3":103},
    {"p1":100,
     "p2":101,
     "p3":103},
    {"p1":0,
     "p2":1,
     "p3":103},
    {"p1":0,
     "p2":103,
     "p3":104},
    {"p1":44,
     "p2":45,
     "p3":46},
    {"p1":44,
     "p2":46,
     "p3":47},
    {"p1":39,
     "p2":49,
     "p3":53},
    {"p1":59,
     "p2":60,
     "p3":61},
    {"p1":58,
     "p2":59,
     "p3":61},
    {"p1":57,
     "p2":61,
     "p3":62},
    {"p1":57,
     "p2":58,
     "p3":61},
    {"p1":55,
     "p2":56,
     "p3":57},
    {"p1":12,
     "p2":87,
     "p3":88},
    {"p1":12,
     "p2":86,
     "p3":87},
    {"p1":12,
     "p2":14,
     "p3":86},
    {"p1":12,
     "p2":13,
     "p3":14},
    {"p1":14,
     "p2":84,
     "p3":86},
    {"p1":14,
     "p2":15,
     "p3":83},
    {"p1":14,
     "p2":83,
     "p3":84},
    {"p1":12,
     "p2":88,
     "p3":89},
    {"p1":35,
     "p2":36,
     "p3":70},
    {"p1":40,
     "p2":41,
     "p3":49},
    {"p1":39,
     "p2":40,
     "p3":49},
    {"p1":49,
     "p2":50,
     "p3":53},
    {"p1":11,
     "p2":89,
     "p3":90},
    {"p1":11,
     "p2":12,
     "p3":89},
    {"p1":18,
     "p2":78,
     "p3":79},
    {"p1":18,
     "p2":79,
     "p3":80},
    {"p1":15,
     "p2":82,
     "p3":83},
    {"p1":15,
     "p2":16,
     "p3":82},
    {"p1":7,
     "p2":96,
     "p3":97},
    {"p1":5,
     "p2":6,
     "p3":7},
    {"p1":5,
     "p2":7,
     "p3":97},
    {"p1":84,
     "p2":85,
     "p3":86},
    {"p1":71,
     "p2":72,
     "p3":73},
    {"p1":70,
     "p2":71,
     "p3":73},
    {"p1":35,
     "p2":70,
     "p3":73},
    {"p1":36,
     "p2":37,
     "p3":70},
    {"p1":50,
     "p2":51,
     "p3":52},
    {"p1":50,
     "p2":52,
     "p3":53},
    {"p1":41,
     "p2":42,
     "p3":49},
    {"p1":43,
     "p2":44,
     "p3":48},
    {"p1":44,
     "p2":47,
     "p3":48},
    {"p1":42,
     "p2":43,
     "p3":48},
    {"p1":42,
     "p2":48,
     "p3":49},
    {"p1":31,
     "p2":32,
     "p3":74},
    {"p1":31,
     "p2":74,
     "p3":75},
    {"p1":30,
     "p2":31,
     "p3":75},
    {"p1":23,
     "p2":24,
     "p3":26},
    {"p1":24,
     "p2":25,
     "p3":26},
    {"p1":38,
     "p2":39,
     "p3":53},
    {"p1":28,
     "p2":75,
     "p3":76},
    {"p1":20,
     "p2":21,
     "p3":28},
    {"p1":10,
     "p2":11,
     "p3":90},
    {"p1":10,
     "p2":90,
     "p3":91},
    {"p1":10,
     "p2":91,
     "p3":92},
    {"p1":10,
     "p2":92,
     "p3":93},
    {"p1":9,
     "p2":10,
     "p3":93},
    {"p1":18,
     "p2":80,
     "p3":81},
    {"p1":17,
     "p2":18,
     "p3":81},
    {"p1":16,
     "p2":17,
     "p3":81},
    {"p1":16,
     "p2":81,
     "p3":82},
    {"p1":19,
     "p2":76,
     "p3":77},
    {"p1":19,
     "p2":28,
     "p3":76},
    {"p1":19,
     "p2":20,
     "p3":28},
    {"p1":18,
     "p2":19,
     "p3":78},
    {"p1":19,
     "p2":77,
     "p3":78},
    {"p1":4,
     "p2":5,
     "p3":97},
    {"p1":8,
     "p2":9,
     "p3":93},
    {"p1":8,
     "p2":93,
     "p3":94},
    {"p1":7,
     "p2":8,
     "p3":94},
    {"p1":38,
     "p2":53,
     "p3":66},
    {"p1":53,
     "p2":54,
     "p3":66},
    {"p1":57,
     "p2":63,
     "p3":64},
    {"p1":55,
     "p2":57,
     "p3":64},
    {"p1":54,
     "p2":55,
     "p3":64},
    {"p1":54,
     "p2":64,
     "p3":66},
    {"p1":64,
     "p2":65,
     "p3":66},
    {"p1":32,
     "p2":33,
     "p3":74},
    {"p1":33,
     "p2":73,
     "p3":74},
    {"p1":29,
     "p2":30,
     "p3":75},
    {"p1":28,
     "p2":29,
     "p3":75},
    {"p1":21,
     "p2":22,
     "p3":27},
    {"p1":21,
     "p2":27,
     "p3":28},
    {"p1":22,
     "p2":23,
     "p3":27},
    {"p1":23,
     "p2":26,
     "p3":27},
    {"p1":3,
     "p2":4,
     "p3":99},
    {"p1":2,
     "p2":3,
     "p3":99},
    {"p1":1,
     "p2":99,
     "p3":100},
    {"p1":1,
     "p2":2,
     "p3":99},
    {"p1":7,
     "p2":95,
     "p3":96},
    {"p1":7,
     "p2":94,
     "p3":95},
    {"p1":34,
     "p2":35,
     "p3":73},
    {"p1":33,
     "p2":34,
     "p3":73},
    {"p1":4,
     "p2":97,
     "p3":98},
    {"p1":4,
     "p2":98,
     "p3":99},
    {"p1":66,
     "p2":67,
     "p3":68},
    {"p1":37,
     "p2":38,
     "p3":68},
    {"p1":38,
     "p2":66,
     "p3":68},
    {"p1":68,
     "p2":69,
     "p3":70},
    {"p1":37,
     "p2":68,
     "p3":70}]
}